scraper/__init__.py
scraper/abstract_doc/AbstractDoc.py
scraper/abstract_doc/__init__.py
scraper/abstract_doc/core/AbstractDocBase.py
scraper/abstract_doc/core/AbstractDocBasePathsMixin.py
scraper/abstract_doc/core/AbstractDocGeneratorMixin.py
scraper/abstract_doc/core/AbstractDocMetadataMixin.py
scraper/abstract_doc/core/AbstractDocRemotePathMixin.py
scraper/abstract_doc/core/AbstractDocTextMixin.py
scraper/abstract_doc/core/__init__.py
scraper/abstract_doc/data_mixins/AbstractTabularMixin.py
scraper/abstract_doc/data_mixins/__init__.py
scraper/abstract_doc/hugging_face/AbstractDocHuggingFaceMixin.py
scraper/abstract_doc/hugging_face/__init__.py
scraper/abstract_doc/pipeline/AbstractDocPipelineCleanupMixin.py
scraper/abstract_doc/pipeline/AbstractDocPipelineExtendedDataMixin.py
scraper/abstract_doc/pipeline/AbstractDocPipelineMetadataMixin.py
scraper/abstract_doc/pipeline/AbstractDocPipelineMixin.py
scraper/abstract_doc/pipeline/__init__.py
scraper/abstract_doc/readme/AbstractDocChartDocsByTimeAndLangMixin.py
scraper/abstract_doc/readme/AbstractDocReadMeMixin.py
scraper/abstract_doc/readme/AbstractDocSummaryMixin.py
scraper/abstract_doc/readme/__init__.py
scraper/abstract_excel_spreadsheet/AbstractExcelSpreadsheet.py
scraper/abstract_excel_spreadsheet/__init__.py
scraper/abstract_pdf_doc/AbstractPDFDoc.py
scraper/abstract_pdf_doc/__init__.py
scraper/global_readme/GlobalReadMe.py
scraper/global_readme/GlobalReadMeSummaryMixin.py
scraper/global_readme/__init__.py
scraper_nuuuwan-1.1.7.dist-info/licenses/LICENSE
scraper_nuuuwan-1.1.7.dist-info/METADATA
scraper_nuuuwan-1.1.7.dist-info/WHEEL
scraper_nuuuwan-1.1.7.dist-info/top_level.txt
scraper_nuuuwan-1.1.7.dist-info/RECORD
