Metadata-Version: 2.4
Name: scraper-nuuuwan
Version: 1.1.7
Summary: Utilities for Scraping Documents from Websites.
Home-page: https://github.com/nuuuwan/scraper
Author: Nuwan I. Senaratna
Author-email: nuuuwan@gmail.com
Project-URL: Bug Tracker, https://github.com/nuuuwan/scraper/issues
Classifier: Programming Language :: Python :: 3
Classifier: License :: OSI Approved :: MIT License
Classifier: Operating System :: OS Independent
Requires-Python: >=3.10
License-File: LICENSE
Requires-Dist: utils-nuuuwan
Requires-Dist: bs4
Requires-Dist: pymupdf
Requires-Dist: matplotlib
Requires-Dist: datasets
Requires-Dist: huggingface_hub
Requires-Dist: pandas
Requires-Dist: numpy
Requires-Dist: selenium
Dynamic: author
Dynamic: author-email
Dynamic: classifier
Dynamic: description-content-type
Dynamic: home-page
Dynamic: license-file
Dynamic: project-url
Dynamic: requires-dist
Dynamic: requires-python
Dynamic: summary
